pyblish_config/__init__.py
pyblish_config/config.py
pyblish_config-0.0.2.dist-info/LICENSE
pyblish_config-0.0.2.dist-info/METADATA
pyblish_config-0.0.2.dist-info/WHEEL
pyblish_config-0.0.2.dist-info/top_level.txt
pyblish_config-0.0.2.dist-info/RECORD
