Metadata-Version: 2.1
Name: pyblish-config
Version: 0.0.2
Summary: Control the flow and settings of your Pyblish plugins with config files
Author: Hannes D
Project-URL: Homepage, https://github.com/hannesdelbeke/pyblish-config
Project-URL: Source, https://github.com/hannesdelbeke/pyblish-config
Keywords: plugin,addon,add-on,extension,manager,studio,dcc,pipeline
Classifier: Programming Language :: Python :: 3.7
Requires-Python: >=3.4
License-File: LICENSE
Requires-Dist: pyblish-base
Requires-Dist: importlib-metadata ; python_version < "3.7"
